pylogr/__init__.py
pylogr/pylogr.py
pylogr-0.1.0.dist-info/licenses/LICENSE
pylogr-0.1.0.dist-info/METADATA
pylogr-0.1.0.dist-info/WHEEL
pylogr-0.1.0.dist-info/top_level.txt
pylogr-0.1.0.dist-info/RECORD
